headerfiles/__init__.py
headerfiles/api.py
headerfiles/cli.py
headerfiles/__pycache__/__init__.cpython-310.pyc
headerfiles/__pycache__/api.cpython-310.pyc
headerfiles/__pycache__/cli.cpython-310.pyc
headerfiles/data/headerfiles.json
headerfiles/data/headerfiles.json.bk
headerfiles-0.4.dist-info/LICENSE
headerfiles-0.4.dist-info/METADATA
headerfiles-0.4.dist-info/WHEEL
headerfiles-0.4.dist-info/entry_points.txt
headerfiles-0.4.dist-info/top_level.txt
headerfiles-0.4.dist-info/RECORD
