Metadata-Version: 2.1
Name: headerfiles
Version: 0.4
Summary: Header files inference for C/C++ projects
Home-page: https://github.com/occia/headerfiles
Author: Cen Zhang
Author-email: blbllhy@gmail.com
License: UNKNOWN
Platform: UNKNOWN
Classifier: Programming Language :: Python :: 3
Classifier: Operating System :: OS Independent
Requires-Python: >=3.7
License-File: LICENSE
Requires-Dist: click
Provides-Extra: dev
Requires-Dist: pytest ; extra == 'dev'
